sweepexp/__init__.py
sweepexp/logger.py
sweepexp/sweepexp.py
sweepexp/sweepexp_mpi.py
sweepexp/sweepexp_parallel.py
sweepexp/sweepexp_sequential.py
sweepexp-1.1.1.dist-info/licenses/LICENSE
sweepexp-1.1.1.dist-info/METADATA
sweepexp-1.1.1.dist-info/WHEEL
sweepexp-1.1.1.dist-info/top_level.txt
sweepexp-1.1.1.dist-info/RECORD
