Metadata-Version: 2.4
Name: sweepexp
Version: 1.1.1
Summary: A python package for running parallel experiments across parameter grids with MPI.
Author-email: Silvano Gordian Rosenau <silvano.rosenau@uni-hamburg.de>
License: MIT License
Project-URL: Repository, https://github.com/Gordi42/sweepexp
Classifier: Programming Language :: Python :: 3
Classifier: License :: OSI Approved :: MIT License
Classifier: Operating System :: OS Independent
Classifier: Development Status :: 5 - Production/Stable
Requires-Python: >=3.10
License-File: LICENSE
Requires-Dist: lazypimp
Requires-Dist: xarray
Requires-Dist: dill
Provides-Extra: full
Requires-Dist: zarr; extra == "full"
Requires-Dist: netCDF4; extra == "full"
Dynamic: license-file
